{
  "swagger": "2.0",
  "info": {
    "title": "managementpb/dbaas/logs.proto",
    "version": "version not set"
  },
  "consumes": [
    "application/json"
  ],
  "produces": [
    "application/json"
  ],
  "paths": {
    "/v1/management/DBaaS/GetLogs": {
      "post": {
        "summary": "GetLogs gets all logs from db cluster.",
        "operationId": "GetLogs",
        "responses": {
          "200": {
            "description": "A successful response.",
            "schema": {
              "$ref": "#/definitions/v1beta1GetLogsResponse"
            }
          },
          "default": {
            "description": "An unexpected error response.",
            "schema": {
              "$ref": "#/definitions/runtimeError"
            }
          }
        },
        "parameters": [
          {
            "name": "body",
            "in": "body",
            "required": true,
            "schema": {
              "$ref": "#/definitions/v1beta1GetLogsRequest"
            }
          }
        ],
        "tags": [
          "LogsAPI"
        ]
      }
    }
  },
  "definitions": {
    "protobufAny": {
      "type": "object",
      "properties": {
        "type_url": {
          "type": "string"
        },
        "value": {
          "type": "string",
          "format": "byte"
        }
      }
    },
    "runtimeError": {
      "type": "object",
      "properties": {
        "error": {
          "type": "string"
        },
        "code": {
          "type": "integer",
          "format": "int32"
        },
        "message": {
          "type": "string"
        },
        "details": {
          "type": "array",
          "items": {
            "$ref": "#/definitions/protobufAny"
          }
        }
      }
    },
    "v1beta1GetLogsRequest": {
      "type": "object",
      "properties": {
        "kubernetes_cluster_name": {
          "type": "string",
          "description": "Kubernetes cluster name."
        },
        "cluster_name": {
          "type": "string",
          "description": "DB cluster name."
        }
      }
    },
    "v1beta1GetLogsResponse": {
      "type": "object",
      "properties": {
        "logs": {
          "type": "array",
          "items": {
            "$ref": "#/definitions/v1beta1Logs"
          },
          "description": "Log represents list of logs. Each entry contains either container's logs or,\nwhen container field is empty, pod's events."
        }
      }
    },
    "v1beta1Logs": {
      "type": "object",
      "properties": {
        "pod": {
          "type": "string",
          "description": "Pod name."
        },
        "container": {
          "type": "string",
          "description": "Container name."
        },
        "logs": {
          "type": "array",
          "items": {
            "type": "string"
          },
          "description": "Content of container's log or pod's events."
        }
      },
      "description": "Logs contain logs for certain pod's container. If container is an empty\nstring, logs contain pod's events."
    }
  }
}
